{
  "metadata": { "id": "map8", "name": "Sports Complex", "description": "Sports grounds & stadium", "version": "2.0", "author": "Game Developer" },
  "dimensions": { "width": 16, "height": 12 },
  "tiles": [
    "FFFFFFFF.FFFFFFF",
    "F..............F",
    "F.CCCC....CCCC.F",
    "F.C..C....C..C.F",
    "F.C..C....C..C.F",
    "F.CCCC....CCCC.F",
    "F..............F",
    "E......P.......F",
    "F..FFFFFFFFFF..F",
    "F..F........F..F",
    "F..FFFFFFFFFF..F",
    "FFFFFFFFFFFFFFFF"
  ],
  "tile_legend": { "F": "GREEN_FIELD", "C": "CAFETERIA", ".": "FLOOR", "P": "PLAYER_SPAWN", "E": "EXIT" },
  "spawn_points": {
    "default": { "x": 8, "y": 7, "description": "Sports center" },
    "from_map4": { "x": 6, "y": 0, "description": "From desert (north)" },
    "from_map7": { "x": 0, "y": 6, "description": "From dorms (west)" }
  },
  "transitions": [
    { "from_position": { "x": 6, "y": 0 }, "to_map": "map4", "to_spawn": "from_map8" },
    { "from_position": { "x": 0, "y": 6 }, "to_map": "map7", "to_spawn": "from_map8" }
  ]
}
